ubotadapter/__init__.py
ubotadapter/botadapter.py
ubotadapter/botconfig.py
ubotadapter/botcontext.py
ubotadapter/botdebug.py
ubotadapter/botinfo.py
ubotadapter/botmsg.py
ubotadapter/enums.py
ubotadapter/inbound.py
ubotadapter/logger.py
ubotadapter/manager.py
ubotadapter/msgfilter.py
ubotadapter/uhttp.py
ubotadapter/user.py
ubotadapter/bots/__init__.py
ubotadapter/bots/channel.py
ubotadapter/bots/dtf/__init__.py
ubotadapter/bots/dtf/dtf.py
ubotadapter/bots/dtf/inbound.py
ubotadapter/bots/dtf/user.py
ubotadapter/bots/telegram/__init__.py
ubotadapter/bots/telegram/inbound.py
ubotadapter/bots/telegram/tg.py
ubotadapter/bots/telegram/user.py
ubotadapter/bots/vk/__init__.py
ubotadapter/bots/vk/inbound.py
ubotadapter/bots/vk/user.py
ubotadapter/bots/vk/vk.py
ubotadapter/test/__init__.py
ubotadapter/test/test_basic.py
ubotadapter/test/test_bot.py
ubotadapter/test/test_common.py
ubotadapter/test/test_data.py
ubotadapter/test/test_dtf.py
ubotadapter/test/test_tools.py
ubotadapter/test/test_webhook.py
ubotadapter/test/tgtest.py
ubotadapter/test/vktest.py
ubotadapter-0.3.7.dist-info/LICENSE
ubotadapter-0.3.7.dist-info/METADATA
ubotadapter-0.3.7.dist-info/WHEEL
ubotadapter-0.3.7.dist-info/top_level.txt
ubotadapter-0.3.7.dist-info/RECORD
