Metadata-Version: 2.1
Name: ubotadapter
Version: 0.3.7
Summary: Bot Adapter class
Home-page: UNKNOWN
Author: Smyek
Author-email: smyek.job@gmail.com
License: MIT
Platform: UNKNOWN
License-File: LICENSE
Requires-Dist: backoff
Requires-Dist: vkale (==0.4.2)
Requires-Dist: python-telegram-bot
Requires-Dist: deteefapi (==0.4.2)
